{
  "OMCWExtension": {},
  "Address": {},
  "frameType": "Page",
  "pageData": {
    "pageNumber": 51,
    "lineCount": 9,
    "pageAttributes": {
      "freeze": false,
      "advisory": false,
      "warning": false,
      "flip": false,
      "roll": false,
      "chain": false
    },
    "lineAttributes": [
      {
        "seperator": false,
        "flash": false,
        "reverse": false,
        "border": true,
        "color": 5
      },
      {
        "seperator": false,
        "flash": false,
        "reverse": false,
        "border": true,
        "color": 5
      },
      {
        "seperator": false,
        "flash": false,
        "reverse": false,
        "border": true,
        "color": 5
      },
      {
        "seperator": false,
        "flash": false,
        "reverse": false,
        "border": true,
        "color": 5
      },
      {
        "seperator": false,
        "flash": false,
        "reverse": false,
        "border": true,
        "color": 5
      },
      {
        "seperator": false,
        "flash": false,
        "reverse": false,
        "border": true,
        "color": 5
      },
      {
        "seperator": false,
        "flash": false,
        "reverse": false,
        "border": true,
        "color": 5
      },
      {
        "seperator": false,
        "flash": false,
        "reverse": false,
        "border": true,
        "color": 5
      },
      {
        "seperator": false,
        "flash": false,
        "reverse": false,
        "border": true,
        "color": 5
      }
    ],
    "lines": [
      {
        "rowNumber": 1,
        "heightWidth": {
          "height": 1,
          "width": 0
        },
        "textData": "str_line1"
      },
      {
        "rowNumber": 2,
        "heightWidth": {
          "height": 1,
          "width": 0
        },
        "textData": "str_line2"
      },
      {
        "rowNumber": 3,
        "heightWidth": {
          "height": 1,
          "width": 0
        },
        "textData": "str_line3"
      },
      {
      	"rowNumber": 4,
	"heightWidth": {
	  "height": 1,
	  "width": 0
	},
	"textData": "str_line4"
      },
      {
      	"rowNumber": 5,
	"heightWidth": {
	  "height": 1,
	  "width": 0
	},
	"textData": "str_line5"
      },
      {
      	"rowNumber": 6,
	"heightWidth": {
	  "height": 1,
	  "width": 0
	},
	"textData": "str_line6"
      },
      {
      	"rowNumber": 7,
	"heightWidth": {
	  "height": 1,
	  "width": 0
	},
	"textData": "str_line7"
      },
      {
      	"rowNumber": 8,
	"heightWidth": {
	  "height": 1,
	  "width": 0
	},
	"textData": "str_line8"
      },
      {
      	"rowNumber": 9,
	"heightWidth": {
	  "height": 0,
	  "width": 0
	},
	"textData": "str_line9"
      }
    ]
  }
}
